AOT_biomaps/Config.py
AOT_biomaps/Settings.py
AOT_biomaps/__init__.py
AOT_biomaps/AOT_Acoustic/AcousticEnums.py
AOT_biomaps/AOT_Acoustic/AcousticTools.py
AOT_biomaps/AOT_Acoustic/FocusedWave.py
AOT_biomaps/AOT_Acoustic/IrregularWave.py
AOT_biomaps/AOT_Acoustic/PlaneWave.py
AOT_biomaps/AOT_Acoustic/StructuredWave.py
AOT_biomaps/AOT_Acoustic/__init__.py
AOT_biomaps/AOT_Acoustic/_mainAcoustic.py
AOT_biomaps/AOT_Experiment/ExperimentTools.py
AOT_biomaps/AOT_Experiment/Focus.py
AOT_biomaps/AOT_Experiment/Tomography.py
AOT_biomaps/AOT_Experiment/__init__.py
AOT_biomaps/AOT_Experiment/_mainExperiment.py
AOT_biomaps/AOT_Optic/Absorber.py
AOT_biomaps/AOT_Optic/Laser.py
AOT_biomaps/AOT_Optic/OpticEnums.py
AOT_biomaps/AOT_Optic/__init__.py
AOT_biomaps/AOT_Optic/_mainOptic.py
AOT_biomaps/AOT_Recon/AOT_biomaps_kernels.cubin
AOT_biomaps/AOT_Recon/AlgebraicRecon.py
AOT_biomaps/AOT_Recon/AnalyticRecon.py
AOT_biomaps/AOT_Recon/BayesianRecon.py
AOT_biomaps/AOT_Recon/DeepLearningRecon.py
AOT_biomaps/AOT_Recon/PrimalDualRecon.py
AOT_biomaps/AOT_Recon/ReconEnums.py
AOT_biomaps/AOT_Recon/ReconTools.py
AOT_biomaps/AOT_Recon/__init__.py
AOT_biomaps/AOT_Recon/_mainRecon.py
AOT_biomaps/AOT_Recon/AOT_Optimizers/DEPIERRO.py
AOT_biomaps/AOT_Recon/AOT_Optimizers/LS.py
AOT_biomaps/AOT_Recon/AOT_Optimizers/MAPEM.py
AOT_biomaps/AOT_Recon/AOT_Optimizers/MLEM.py
AOT_biomaps/AOT_Recon/AOT_Optimizers/PDHG.py
AOT_biomaps/AOT_Recon/AOT_Optimizers/__init__.py
AOT_biomaps/AOT_Recon/AOT_PotentialFunctions/Huber.py
AOT_biomaps/AOT_Recon/AOT_PotentialFunctions/Quadratic.py
AOT_biomaps/AOT_Recon/AOT_PotentialFunctions/RelativeDifferences.py
AOT_biomaps/AOT_Recon/AOT_PotentialFunctions/__init__.py
AOT_biomaps/AOT_Recon/AOT_SparseSMatrix/SparseSMatrix_CSR.py
AOT_biomaps/AOT_Recon/AOT_SparseSMatrix/SparseSMatrix_SELL.py
AOT_biomaps/AOT_Recon/AOT_SparseSMatrix/__init__.py
aot_biomaps-2.9.377.dist-info/METADATA
aot_biomaps-2.9.377.dist-info/WHEEL
aot_biomaps-2.9.377.dist-info/top_level.txt
aot_biomaps-2.9.377.dist-info/RECORD
